openfisca_nouvelle_caledonie/__init__.py
openfisca_nouvelle_caledonie/entities.py
openfisca_nouvelle_caledonie/units.yaml
openfisca_nouvelle_caledonie/parameters/marche_travail/remuneration_fonction_publique/ajustement_duree_echelon.yml
openfisca_nouvelle_caledonie/parameters/marche_travail/remuneration_fonction_publique/mois_retraite.yml
openfisca_nouvelle_caledonie/parameters/marche_travail/remuneration_fonction_publique/taux_equilibre.yml
openfisca_nouvelle_caledonie/parameters/marche_travail/remuneration_fonction_publique/indemnite_residence/taux.yml
openfisca_nouvelle_caledonie/parameters/marche_travail/remuneration_fonction_publique/mcs/taux_salarie.yml
openfisca_nouvelle_caledonie/parameters/marche_travail/remuneration_fonction_publique/ncj/taux_majoration.yml
openfisca_nouvelle_caledonie/parameters/marche_travail/remuneration_fonction_publique/ncj/taux_patronale.yml
openfisca_nouvelle_caledonie/parameters/marche_travail/remuneration_fonction_publique/ncj/taux_salarie.yaml
openfisca_nouvelle_caledonie/parameters/marche_travail/remuneration_fonction_publique/nmf/taux_patronale.yml
openfisca_nouvelle_caledonie/parameters/marche_travail/remuneration_fonction_publique/nmf/taux_salarie.yml
openfisca_nouvelle_caledonie/parameters/marche_travail/remuneration_fonction_publique/prime/prime_adjoint_direction.yml
openfisca_nouvelle_caledonie/parameters/marche_travail/remuneration_fonction_publique/prime/prime_direction.yml
openfisca_nouvelle_caledonie/parameters/marche_travail/remuneration_fonction_publique/prime/prime_experimentale.yml
openfisca_nouvelle_caledonie/parameters/marche_travail/remuneration_fonction_publique/prime/prime_speciale.yml
openfisca_nouvelle_caledonie/parameters/marche_travail/remuneration_fonction_publique/prime/prime_speciale_technicite.yml
openfisca_nouvelle_caledonie/parameters/marche_travail/remuneration_fonction_publique/prime/prime_stabilite.yml
openfisca_nouvelle_caledonie-19.1.0.dist-info/licenses/LICENSE
openfisca_nouvelle_caledonie-19.1.0.dist-info/METADATA
openfisca_nouvelle_caledonie-19.1.0.dist-info/WHEEL
openfisca_nouvelle_caledonie-19.1.0.dist-info/top_level.txt
openfisca_nouvelle_caledonie-19.1.0.dist-info/RECORD
